{
  "author": {
    "name": "kai zhu",
    "email": "kaizhu256@gmail.com"
  },
  "bin": {
    "db-lite": "lib.db.js"
  },
  "description": "this zero-dependency package will provide a persistent, in-browser database, with a working web-demo",
  "devDependencies": {
    "electron-lite": "github:kaizhu256/node-electron-lite#alpha",
    "utility2": "github:kaizhu256/node-utility2#alpha"
  },
  "engines": {
    "node": ">=4.0"
  },
  "homepage": "https://github.com/kaizhu256/node-db-lite",
  "keywords": [
    "database",
    "embedded",
    "indexeddb",
    "nedb"
  ],
  "license": "MIT",
  "main": "lib.db.js",
  "name": "db-lite",
  "nameAliasPublish": "elasticdb-lite esdb nanodb nedb2",
  "nameLib": "db",
  "nameOriginal": "db-lite",
  "os": [
    "darwin",
    "linux"
  ],
  "repository": {
    "user": "kaizhu256",
    "repo": "node-db-lite",
    "host": "github.com",
    "branch": "master",
    "apiHost": "api.github.com",
    "tarball_url": "https://api.github.com/repos/kaizhu256/node-db-lite/tarball/master",
    "clone_url": "https://github.com/kaizhu256/node-db-lite",
    "https_url": "https://github.com/kaizhu256/node-db-lite",
    "travis_url": "https://travis-ci.org/kaizhu256/node-db-lite",
    "zip_url": "https://github.com/kaizhu256/node-db-lite/archive/master.zip",
    "api_url": "https://api.github.com/repos/kaizhu256/node-db-lite"
  },
  "scripts": {
    "build-ci": "utility2 shReadmeTest build_ci.sh",
    "env": "env",
    "heroku-postbuild": "npm uninstall utility2 2>/dev/null; npm install kaizhu256/node-utility2#alpha && utility2 shDeployHeroku",
    "postinstall": "[ ! -f npm_scripts.sh ] || ./npm_scripts.sh postinstall",
    "start": "PORT=${PORT:-8080} utility2 start test.js",
    "test": "PORT=$(utility2 shServerPortRandom) utility2 test test.js"
  },
  "version": "2017.12.4",
  "_npmVersion": "3.10.10",
  "_nodeVersion": "6.12.0",
  "dist": {
    "shasum": "3e258106d4cebaa578b4c356dab081087f2a6463",
    "tarball": "https://registry.npmjs.org/db-lite/-/db-lite-2017.12.4.tgz"
  },
  "stars": 1,
  "versions": [
    {
      "number": "0.0.1",
      "date": "2016-10-13T14:59:46.397Z"
    },
    {
      "number": "2016.10.1",
      "date": "2016-10-17T12:58:37.799Z"
    },
    {
      "number": "2016.10.2",
      "date": "2016-11-15T04:46:10.305Z"
    },
    {
      "number": "2016.10.3",
      "date": "2016-11-21T02:05:06.704Z"
    },
    {
      "number": "2016.12.1",
      "date": "2016-12-13T13:58:29.852Z"
    },
    {
      "number": "2017.2.1",
      "date": "2017-02-18T08:54:45.662Z"
    },
    {
      "number": "2017.2.2",
      "date": "2017-02-24T04:16:13.761Z"
    },
    {
      "number": "2017.3.16",
      "date": "2017-03-16T20:48:01.256Z"
    },
    {
      "number": "2017.3.29",
      "date": "2017-03-30T14:12:10.306Z"
    },
    {
      "number": "2017.5.25",
      "date": "2017-05-26T04:09:27.887Z"
    },
    {
      "number": "2017.7.24",
      "date": "2017-07-25T06:56:31.855Z"
    },
    {
      "number": "2017.9.16",
      "date": "2017-09-17T16:10:35.395Z"
    },
    {
      "number": "2017.11.7",
      "date": "2017-11-07T16:54:25.091Z"
    },
    {
      "number": "2017.12.4",
      "date": "2017-12-04T17:51:41.324Z"
    }
  ],
  "created": "2016-10-13T14:59:46.397Z",
  "modified": "2017-12-04T17:51:41.324Z",
  "lastPublisher": {
    "name": "kaizhu",
    "email": "kaizhu256@gmail.com"
  },
  "owners": [
    {
      "name": "kaizhu",
      "email": "kaizhu256@gmail.com"
    }
  ]
}