{
  "name": "debugger",
  "version": "0.35.0",
  "description": "Easily debug node scripts and Electron renderer processes",
  "scripts": {
    "test": "echo \"Error: no test specified\" && exit 1",
    "postinstall": "node bin/postinstall.js"
  },
  "bin": {
    "debugger": "./bin/debugger.js"
  },
  "dependencies": {
    "electron-prebuilt": "1.0.2",
    "lodash": "3.10.1",
    "mkdirp": "^0.5.1"
  },
  "author": {
    "name": "Francois Laberge",
    "email": "francoislaberge@gmail.com"
  },
  "license": "MIT",
  "repository": {
    "type": "git",
    "url": "git+https://github.com/francoislaberge/debugger.git"
  },
  "bugs": {
    "url": "https://github.com/francoislaberge/debugger/issues"
  },
  "gitHead": "20e3be7fab24ca59e5655be4e9e0118802038ede",
  "homepage": "https://github.com/francoislaberge/debugger#readme",
  "_id": "debugger@0.35.0",
  "_shasum": "7edb48575ad22e200e496c4d4f2fda83c09e204c",
  "_from": ".",
  "_npmVersion": "2.15.1",
  "_nodeVersion": "4.4.3",
  "_npmUser": {
    "name": "francoislaberge",
    "email": "francoislaberge@gmail.com"
  },
  "dist": {
    "shasum": "7edb48575ad22e200e496c4d4f2fda83c09e204c",
    "tarball": "http://registry.npmjs.org/debugger/-/debugger-0.35.0.tgz"
  },
  "maintainers": [
    {
      "name": "francoislaberge",
      "email": "francoislaberge@gmail.com"
    }
  ],
  "_npmOperationalInternal": {
    "host": "packages-12-west.internal.npmjs.com",
    "tmp": "tmp/debugger-0.35.0.tgz_1464707296645_0.05214728834107518"
  },
  "directories": {}
}