{
  "name": "electron-forge-publisher-nucleus",
  "version": "0.0.1",
  "description": "",
  "main": "index.js",
  "scripts": {
    "test": "echo \"Error: no test specified\" && exit 1"
  },
  "author": "",
  "license": "Apache-2.0",
  "_npmVersion": "3.10.10",
  "_nodeVersion": "6.10.3",
  "dist": {
    "shasum": "12fa8154a98a1ac73409091cbb982c341fa41314",
    "tarball": "https://registry.npmjs.org/electron-forge-publisher-nucleus/-/electron-forge-publisher-nucleus-0.0.1.tgz"
  },
  "versions": [
    {
      "number": "0.0.1",
      "date": "2017-10-07T05:10:19.450Z"
    }
  ],
  "created": "2017-10-07T05:10:19.450Z",
  "modified": "2017-10-07T05:10:19.450Z",
  "lastPublisher": {
    "name": "marshallofsound",
    "email": "samuel.r.attard@gmail.com"
  },
  "owners": [
    {
      "name": "marshallofsound",
      "email": "samuel.r.attard@gmail.com"
    }
  ]
}