{
  "name": "electron-google-analytics",
  "version": "0.0.24",
  "description": "A library to implement Google Analytics in desktop apps.",
  "main": "lib/index.js",
  "scripts": {
    "build": "babel src -d lib",
    "test": "cross-env NODE_ENV=test mocha --compilers js:babel-register"
  },
  "keywords": [
    "google",
    "analytics",
    "google analytics"
  ],
  "author": {
    "name": "Eastercow",
    "email": "eastercowz@gmail.com",
    "url": "http://eastercowz.com"
  },
  "license": "MIT",
  "repository": {
    "user": "vacu",
    "repo": "electron-google-analytics",
    "host": "github.com",
    "branch": "master",
    "apiHost": "api.github.com",
    "tarball_url": "https://api.github.com/repos/vacu/electron-google-analytics/tarball/master",
    "clone_url": "https://github.com/vacu/electron-google-analytics",
    "https_url": "https://github.com/vacu/electron-google-analytics",
    "travis_url": "https://travis-ci.org/vacu/electron-google-analytics",
    "zip_url": "https://github.com/vacu/electron-google-analytics/archive/master.zip",
    "api_url": "https://api.github.com/repos/vacu/electron-google-analytics"
  },
  "devDependencies": {
    "babel-cli": "^6.26.0",
    "babel-core": "^6.26.0",
    "babel-preset-env": "^1.6.1",
    "babel-preset-es2015": "^6.24.1",
    "babel-register": "^6.26.0",
    "chai": "^4.1.2",
    "cross-env": "^5.1.1",
    "eslint": "^4.10.0",
    "eslint-config-airbnb-base": "^12.1.0",
    "eslint-plugin-import": "^2.8.0",
    "mocha": "^4.0.1"
  },
  "dependencies": {
    "request": "^2.83.0",
    "uuid": "^3.1.0"
  },
  "gitHead": "1b8d93f4192b4644f0131525569e0eca267cad4b",
  "homepage": "https://github.com/vacu/electron-google-analytics#readme",
  "_npmVersion": "5.5.1",
  "_nodeVersion": "8.4.0",
  "dist": {
    "integrity": "sha512-PhEhAwsLsuJqI9dbJ3TJiFQHAOOwWSkJixq7vKUZxsIaeW9PC+O13wDjB1uP2DQw5VDeI3hMEGaUuQ5UgbZ0Cg==",
    "shasum": "cc2d0e7a18e9c4c52bda64c8115c70aab80bacdc",
    "tarball": "https://registry.npmjs.org/electron-google-analytics/-/electron-google-analytics-0.0.24.tgz"
  },
  "stars": 2,
  "versions": [
    {
      "number": "0.0.1",
      "date": "2017-02-08T11:31:10.709Z"
    },
    {
      "number": "0.0.2",
      "date": "2017-02-08T11:38:29.086Z"
    },
    {
      "number": "0.0.3",
      "date": "2017-02-08T11:51:44.442Z"
    },
    {
      "number": "0.0.4",
      "date": "2017-02-08T12:37:30.868Z"
    },
    {
      "number": "0.0.5",
      "date": "2017-02-10T16:01:56.193Z"
    },
    {
      "number": "0.0.6",
      "date": "2017-02-10T16:02:57.083Z"
    },
    {
      "number": "0.0.7",
      "date": "2017-02-10T16:05:16.783Z"
    },
    {
      "number": "0.0.8",
      "date": "2017-02-10T16:07:28.021Z"
    },
    {
      "number": "0.0.9",
      "date": "2017-02-12T12:47:05.052Z"
    },
    {
      "number": "0.0.10",
      "date": "2017-02-12T12:49:37.139Z"
    },
    {
      "number": "0.0.11",
      "date": "2017-02-23T22:19:41.784Z"
    },
    {
      "number": "0.0.12",
      "date": "2017-02-23T22:25:03.171Z"
    },
    {
      "number": "0.0.13",
      "date": "2017-03-14T00:06:24.422Z"
    },
    {
      "number": "0.0.14",
      "date": "2017-03-14T00:10:25.688Z"
    },
    {
      "number": "0.0.15",
      "date": "2017-03-14T00:14:08.093Z"
    },
    {
      "number": "0.0.16",
      "date": "2017-03-14T00:28:56.325Z"
    },
    {
      "number": "0.0.17",
      "date": "2017-09-09T19:02:55.406Z"
    },
    {
      "number": "0.0.18",
      "date": "2017-10-28T14:38:32.692Z"
    },
    {
      "number": "0.0.19",
      "date": "2017-10-28T15:03:22.114Z"
    },
    {
      "number": "0.0.20",
      "date": "2017-10-30T11:20:16.464Z"
    },
    {
      "number": "0.0.21",
      "date": "2017-10-30T11:25:25.081Z"
    },
    {
      "number": "0.0.22",
      "date": "2017-10-30T11:26:44.100Z"
    },
    {
      "number": "0.0.23",
      "date": "2017-10-30T11:33:36.757Z"
    },
    {
      "number": "0.0.24",
      "date": "2017-10-31T16:35:21.694Z"
    }
  ],
  "created": "2017-02-08T11:31:10.709Z",
  "modified": "2017-10-31T16:35:21.694Z",
  "lastPublisher": {
    "name": "eastercow",
    "email": "eastercowz@gmail.com"
  },
  "owners": [
    {
      "name": "eastercow",
      "email": "eastercowz@gmail.com"
    }
  ]
}