{
  "name": "electron-adventure",
  "version": "0.0.1",
  "description": " Learn the basic of Electron (formerly atom-shell) with this educational workshop",
  "main": "index.js",
  "scripts": {
    "test": "echo \"Error: no test specified\" && exit 1"
  },
  "repository": {
    "user": "sotayamashita",
    "repo": "electron-adventure",
    "host": "github.com",
    "branch": "master",
    "apiHost": "api.github.com",
    "tarball_url": "https://api.github.com/repos/sotayamashita/electron-adventure/tarball/master",
    "clone_url": "https://github.com/sotayamashita/electron-adventure",
    "https_url": "https://github.com/sotayamashita/electron-adventure",
    "travis_url": "https://travis-ci.org/sotayamashita/electron-adventure",
    "zip_url": "https://github.com/sotayamashita/electron-adventure/archive/master.zip",
    "api_url": "https://api.github.com/repos/sotayamashita/electron-adventure"
  },
  "keywords": [
    "electron",
    "atom-shell",
    "learn",
    "workshopper",
    "adventure",
    "tutorial"
  ],
  "author": {
    "name": "Sota Yamashita"
  },
  "license": "MIT",
  "bin": {
    "electron-adventure": "./electron.js"
  },
  "homepage": "https://github.com/sotayamashita/electron-adventure#readme",
  "devDependencies": {
    "workshopper-adventure": "^3.4.5",
    "workshopper-exercise": "^2.4.0"
  },
  "gitHead": "ad268ab9c3ca99215b5fa9b7389e1b644418407a",
  "_npmVersion": "2.10.0",
  "_nodeVersion": "0.12.7",
  "dist": {
    "shasum": "3e25507e69f4c16b119811cc620b154565576e22",
    "tarball": "http://registry.npmjs.org/electron-adventure/-/electron-adventure-0.0.1.tgz"
  },
  "versions": [
    {
      "number": "0.0.1",
      "date": "2015-08-12T08:33:48.641Z"
    }
  ],
  "created": "2015-08-12T08:33:48.641Z",
  "modified": "2015-08-12T08:33:48.641Z",
  "lastPublisher": {
    "name": "sotayamashita",
    "email": "sota.yamashita@gmail.com"
  },
  "owners": [
    {
      "name": "sotayamashita",
      "email": "sota.yamashita@gmail.com"
    }
  ],
  "readme": "# Electron Adventure\n\n:package: Learn the basic of Electron (formerly atom-shell) with this educational workshop\n\n## Install\n\n```bash\n$ npm install -g electron-adventure\n```\n\nThen you will have a `electron-adventure` command:\n\n```\n$ electron-adventure\n```\n\n## License\n\nMIT © [Sota Yamashita](https://github.com/sotayamashita)\n"
}