{
  "name": "electron-ipc-reactive",
  "version": "1.0.6",
  "description": "Reactive Elements for Electron via IPC",
  "main": "ipcRenderer.js",
  "repository": {
    "user": "simonhochrein",
    "repo": "electron-ipc-reactive",
    "host": "github.com",
    "branch": "master",
    "apiHost": "api.github.com",
    "tarball_url": "https://api.github.com/repos/simonhochrein/electron-ipc-reactive/tarball/master",
    "clone_url": "https://github.com/simonhochrein/electron-ipc-reactive",
    "https_url": "https://github.com/simonhochrein/electron-ipc-reactive",
    "travis_url": "https://travis-ci.org/simonhochrein/electron-ipc-reactive",
    "zip_url": "https://github.com/simonhochrein/electron-ipc-reactive/archive/master.zip",
    "api_url": "https://api.github.com/repos/simonhochrein/electron-ipc-reactive"
  },
  "scripts": {
    "start": "electron app.js"
  },
  "author": "",
  "license": "ISC",
  "keywords": [
    "electron",
    "bind",
    "reactive"
  ],
  "gitHead": "2816f1a21539360f32ec244da3921d05bdfb4331",
  "homepage": "https://github.com/simonhochrein/electron-ipc-reactive#readme",
  "_npmVersion": "3.9.5",
  "_nodeVersion": "6.2.2",
  "dist": {
    "shasum": "efcd70bf6b33895e7138eb163e446cb33e74d14d",
    "tarball": "http://registry.npmjs.org/electron-ipc-reactive/-/electron-ipc-reactive-1.0.6.tgz"
  },
  "versions": [
    {
      "number": "1.0.2",
      "date": "2016-06-20T13:22:54.431Z"
    },
    {
      "number": "1.0.3",
      "date": "2016-06-20T13:23:40.742Z"
    },
    {
      "number": "1.0.4",
      "date": "2016-06-20T13:26:32.709Z"
    },
    {
      "number": "1.0.6",
      "date": "2016-06-20T15:17:25.198Z"
    }
  ],
  "created": "2016-06-20T13:22:54.431Z",
  "modified": "2016-06-20T15:17:25.198Z",
  "lastPublisher": {
    "name": "simon.hochrein",
    "email": "simon@ministrycrm.com"
  },
  "owners": [
    {
      "name": "simon.hochrein",
      "email": "simon@ministrycrm.com"
    }
  ]
}