{
  "name": "electron-sqlite",
  "version": "0.0.1",
  "description": "",
  "repository": {
    "user": "parro-it",
    "repo": "electron-sqlite",
    "host": "github.com",
    "branch": "master",
    "apiHost": "api.github.com",
    "tarball_url": "https://api.github.com/repos/parro-it/electron-sqlite/tarball/master",
    "clone_url": "https://github.com/parro-it/electron-sqlite",
    "https_url": "https://github.com/parro-it/electron-sqlite",
    "travis_url": "https://travis-ci.org/parro-it/electron-sqlite",
    "zip_url": "https://github.com/parro-it/electron-sqlite/archive/master.zip",
    "api_url": "https://api.github.com/repos/parro-it/electron-sqlite"
  },
  "license": "MIT",
  "author": {
    "name": "parro-it"
  },
  "scripts": {
    "test": "eslint . && node test | faucet"
  },
  "keywords": [],
  "engines": {
    "node": ">=5"
  },
  "eslintConfig": {
    "extends": [
      "js",
      "features"
    ]
  },
  "devDependencies": {
    "eslint": "^1.10.3",
    "eslint-config-features": "^1.1.5",
    "eslint-config-js": "^4.0.0",
    "faucet": "0.0.1",
    "tape": "^4.2.2"
  },
  "files": [
    "index.js"
  ],
  "gitHead": "6546d09a3eaa96114bcd8e9574d8caeb72fb3b98",
  "homepage": "https://github.com/parro-it/electron-sqlite#readme",
  "_npmVersion": "3.3.6",
  "_nodeVersion": "5.0.0",
  "dist": {
    "shasum": "1812b002a878ef6c34d70f74bf5276de11abd6e4",
    "tarball": "http://registry.npmjs.org/electron-sqlite/-/electron-sqlite-0.0.1.tgz"
  },
  "stars": 1,
  "versions": [
    {
      "number": "0.0.1",
      "date": "2016-03-28T18:36:00.719Z"
    }
  ],
  "created": "2016-03-28T18:36:00.719Z",
  "modified": "2017-07-20T18:38:23.705Z",
  "lastPublisher": {
    "name": "parroit",
    "email": "andrea@parro.it"
  },
  "owners": [
    {
      "name": "parroit",
      "email": "andrea@parro.it"
    }
  ]
}