{
  "name": "electron-zip-packager",
  "repository": {
    "user": "azu",
    "repo": "electron-zip-packager",
    "host": "github.com",
    "branch": "master",
    "apiHost": "api.github.com",
    "tarball_url": "https://api.github.com/repos/azu/electron-zip-packager/tarball/master",
    "clone_url": "https://github.com/azu/electron-zip-packager",
    "https_url": "https://github.com/azu/electron-zip-packager",
    "travis_url": "https://travis-ci.org/azu/electron-zip-packager",
    "zip_url": "https://github.com/azu/electron-zip-packager/archive/master.zip",
    "api_url": "https://api.github.com/repos/azu/electron-zip-packager"
  },
  "author": {
    "name": "azu"
  },
  "email": "azuciao@gmail.com",
  "homepage": "https://github.com/azu/electron-zip-packager",
  "license": "MIT",
  "version": "4.0.2",
  "description": "A wrapper of electron-packager. Package your electron app and zipped!",
  "keywords": [
    "electron",
    "zip",
    "package"
  ],
  "main": "lib/archive-zip.js",
  "files": [
    "bin",
    "lib"
  ],
  "bin": {
    "electron-zip-packager": "bin/cmd.js"
  },
  "scripts": {
    "travis-test": "(cd example && yarn install && npm run dist)"
  },
  "dependencies": {
    "archiver": "^1.3.0",
    "electron-packager": "^8.6.0",
    "minimist": "^1.2.0",
    "electron": "^1.6.2"
  },
  "gitHead": "3b7a402fc366975ae1ed5b9d66c659fca6cab525",
  "_npmVersion": "4.1.2",
  "_nodeVersion": "7.7.2",
  "dist": {
    "shasum": "bfe197d1a23f027087ae4a71433bcabcd8f1b809",
    "tarball": "https://registry.npmjs.org/electron-zip-packager/-/electron-zip-packager-4.0.2.tgz"
  },
  "versions": [
    {
      "number": "1.0.1",
      "date": "2015-07-23T15:53:46.587Z"
    },
    {
      "number": "1.0.2",
      "date": "2015-07-23T16:02:02.690Z"
    },
    {
      "number": "1.0.3",
      "date": "2015-07-25T04:54:53.305Z"
    },
    {
      "number": "1.0.4",
      "date": "2015-11-29T11:47:09.633Z"
    },
    {
      "number": "2.0.0",
      "date": "2016-06-25T12:03:27.099Z"
    },
    {
      "number": "3.0.0",
      "date": "2016-08-18T03:58:20.235Z"
    },
    {
      "number": "4.0.0",
      "date": "2016-09-29T01:14:14.087Z"
    },
    {
      "number": "4.0.1",
      "date": "2016-12-22T05:39:36.357Z"
    },
    {
      "number": "4.0.2",
      "date": "2017-03-17T22:41:34.747Z"
    }
  ],
  "created": "2015-07-23T15:53:46.587Z",
  "modified": "2017-03-17T22:41:34.747Z",
  "lastPublisher": {
    "name": "willyb321",
    "email": "wbwilliam7@gmail.com"
  },
  "owners": [
    {
      "name": "azu",
      "email": "azuciao@gmail.com"
    },
    {
      "name": "willyb321",
      "email": "wbwilliam7@gmail.com"
    }
  ]
}