{
  "name": "electron-menu-loader",
  "version": "0.0.3",
  "description": "Loading a menu template for app running on current platform",
  "license": "MIT",
  "repository": {
    "type": "git",
    "url": "git+https://github.com/ragingwind/electron-menu-loader.git"
  },
  "author": {
    "name": "ragingwind",
    "email": "ragingwind@gmail.com",
    "url": "ragingwind.me"
  },
  "engines": {
    "node": ">=4"
  },
  "scripts": {
    "test": "xo"
  },
  "files": [
    "index.js"
  ],
  "keywords": [
    "electron",
    "electron-menu",
    "electron-menu-loader"
  ],
  "xo": {
    "esnext": true,
    "envs": [
      "node"
    ]
  },
  "jshintConfig": {
    "esnext": true,
    "node": true
  },
  "gitHead": "06869543b67b1288d1eedc09a27a92ce08d1a10c",
  "bugs": {
    "url": "https://github.com/ragingwind/electron-menu-loader/issues"
  },
  "homepage": "https://github.com/ragingwind/electron-menu-loader#readme",
  "_id": "electron-menu-loader@0.0.3",
  "_shasum": "1c959c9267bcb5bb1305c0c5821360a73c167711",
  "_from": ".",
  "_npmVersion": "2.11.3",
  "_nodeVersion": "0.12.7",
  "_npmUser": {
    "name": "ragingwind",
    "email": "ragingwind@gmail.com"
  },
  "dist": {
    "shasum": "1c959c9267bcb5bb1305c0c5821360a73c167711",
    "tarball": "http://registry.npmjs.org/electron-menu-loader/-/electron-menu-loader-0.0.3.tgz"
  },
  "maintainers": [
    {
      "name": "ragingwind",
      "email": "ragingwind@gmail.com"
    }
  ],
  "directories": {}
}