{
  "name": "live-doc-sdk",
  "version": "1.1.25",
  "description": "'just for new-live-doc'",
  "main": "dist/index.js",
  "scripts": {
    "test": "echo \"Error: no test specified\" && exit 1",
    "prepublish": "rm -rf ./dist &&tsc && lessc --clean-css --no-ie-compat ./src/widgets/index.less > ./dist/styles.css"
  },
  "author": {
    "name": "paithink"
  },
  "license": "ISC",
  "dependencies": {
    "rc-animate": "2.3.0",
    "event-emitter": "0.3.4"
  },
  "devDependencies": {
    "@types/mousetrap": "1.5.33",
    "@types/react": "^15.0.24",
    "@types/react-dom": "^15.5.0",
    "@types/webpack-env": "^1.13.0",
    "electron": "1.6.11",
    "less": "^2.7.2",
    "less-plugin-clean-css": "^1.5.1",
    "react": "15.4.1",
    "react-dom": "15.4.1",
    "tslint": "4.1.1",
    "typescript": "^2.3.4",
    "web-webpack-plugin": "^1.5.8",
    "webpack": "^2.6.0"
  },
  "types": "./typings/liveDocSdk.d.ts",
  "_npmVersion": "3.10.9",
  "_nodeVersion": "6.9.2",
  "dist": {
    "shasum": "2cffe406e71f20ecf86d644b28c7c7d4e38a0664",
    "tarball": "https://registry.npmjs.org/live-doc-sdk/-/live-doc-sdk-1.1.25.tgz"
  },
  "versions": [
    {
      "number": "1.0.0",
      "date": "2017-06-13T03:10:06.577Z"
    },
    {
      "number": "1.0.1",
      "date": "2017-06-13T03:19:38.164Z"
    },
    {
      "number": "1.0.2",
      "date": "2017-06-13T03:47:58.890Z"
    },
    {
      "number": "1.0.3",
      "date": "2017-06-13T03:53:06.207Z"
    },
    {
      "number": "1.0.4",
      "date": "2017-06-13T03:54:14.451Z"
    },
    {
      "number": "1.0.5",
      "date": "2017-06-13T09:54:14.190Z"
    },
    {
      "number": "1.1.0",
      "date": "2017-06-15T12:56:42.258Z"
    },
    {
      "number": "1.1.1",
      "date": "2017-06-15T13:19:35.301Z"
    },
    {
      "number": "1.1.2",
      "date": "2017-06-15T13:22:10.986Z"
    },
    {
      "number": "1.1.3",
      "date": "2017-06-15T13:30:04.875Z"
    },
    {
      "number": "1.1.4",
      "date": "2017-06-15T13:58:13.550Z"
    },
    {
      "number": "1.1.5",
      "date": "2017-06-15T14:03:51.661Z"
    },
    {
      "number": "1.1.6",
      "date": "2017-06-15T14:06:00.384Z"
    },
    {
      "number": "1.1.7",
      "date": "2017-06-15T14:06:57.727Z"
    },
    {
      "number": "1.1.8",
      "date": "2017-06-15T14:10:01.311Z"
    },
    {
      "number": "1.1.9",
      "date": "2017-06-16T06:56:12.849Z"
    },
    {
      "number": "1.1.10",
      "date": "2017-06-16T10:27:26.942Z"
    },
    {
      "number": "1.1.11",
      "date": "2017-06-19T05:39:34.405Z"
    },
    {
      "number": "1.1.12",
      "date": "2017-06-19T05:45:29.197Z"
    },
    {
      "number": "1.1.13",
      "date": "2017-06-19T07:38:17.546Z"
    },
    {
      "number": "1.1.14",
      "date": "2017-06-19T08:39:27.878Z"
    },
    {
      "number": "1.1.15",
      "date": "2017-06-19T09:10:04.042Z"
    },
    {
      "number": "1.1.16",
      "date": "2017-06-19T09:24:41.085Z"
    },
    {
      "number": "1.1.17",
      "date": "2017-06-19T09:27:25.318Z"
    },
    {
      "number": "1.1.18",
      "date": "2017-06-19T11:31:21.946Z"
    },
    {
      "number": "1.1.19",
      "date": "2017-06-19T12:17:01.076Z"
    },
    {
      "number": "1.1.20",
      "date": "2017-06-19T12:22:33.477Z"
    },
    {
      "number": "1.1.21",
      "date": "2017-06-19T12:36:42.486Z"
    },
    {
      "number": "1.1.22",
      "date": "2017-06-19T12:40:00.923Z"
    },
    {
      "number": "1.1.23",
      "date": "2017-06-19T12:50:41.621Z"
    },
    {
      "number": "1.1.24",
      "date": "2017-06-19T13:01:56.920Z"
    },
    {
      "number": "1.1.25",
      "date": "2017-06-20T02:33:38.352Z"
    }
  ],
  "created": "2017-06-13T03:10:06.577Z",
  "modified": "2017-06-20T02:33:38.352Z",
  "lastPublisher": {
    "name": "zjfjiayou",
    "email": "441692003@qq.com"
  },
  "owners": [
    {
      "name": "zjfjiayou",
      "email": "441692003@qq.com"
    }
  ]
}