{
  "name": "macaca-wd",
  "version": "1.0.10",
  "description": "macaca wd client",
  "keywords": [
    "macaca",
    "webdriver",
    "wd"
  ],
  "main": "./lib/macaca-wd.js",
  "repository": {
    "user": "macacajs",
    "repo": "macaca-wd",
    "host": "github.com",
    "branch": "master",
    "apiHost": "api.github.com",
    "tarball_url": "https://api.github.com/repos/macacajs/macaca-wd/tarball/master",
    "clone_url": "https://github.com/macacajs/macaca-wd",
    "https_url": "https://github.com/macacajs/macaca-wd",
    "travis_url": "https://travis-ci.org/macacajs/macaca-wd",
    "zip_url": "https://github.com/macacajs/macaca-wd/archive/master.zip",
    "api_url": "https://api.github.com/repos/macacajs/macaca-wd"
  },
  "dependencies": {
    "archiver": "~0.14.0",
    "async": "~1.0.0",
    "lodash": "~3.9.3",
    "q": "~1.4.1",
    "request": "~2.55.0",
    "underscore.string": "~3.0.3",
    "vargs": "~0.1.0",
    "webdriver-keycode": "^1.0.0"
  },
  "devDependencies": {
    "co-mocha": "*",
    "istanbul": "*",
    "jsdoc": "3.4.0",
    "jshint": "*",
    "mocha": "*",
    "pre-commit": "1.1.1",
    "should": "*",
    "startserver": "^1.2.3"
  },
  "scripts": {
    "test": "make test",
    "jshint": "make jshint"
  },
  "pre-commit": [
    "jshint"
  ],
  "homepage": "https://github.com/macacajs/macaca-wd",
  "license": "MIT",
  "gitHead": "30f2ee8cce46b466fa99a996bb75b21959d89fa4",
  "_npmVersion": "3.8.6",
  "_nodeVersion": "6.0.0",
  "dist": {
    "shasum": "faeabc421a08300f035d8b12a763ef95d51407c5",
    "tarball": "http://registry.npmjs.org/macaca-wd/-/macaca-wd-1.0.10.tgz"
  },
  "versions": [
    {
      "number": "0.1.0",
      "date": "2016-04-18T04:34:37.463Z"
    },
    {
      "number": "1.0.0",
      "date": "2016-04-22T08:56:02.026Z"
    },
    {
      "number": "1.0.1",
      "date": "2016-04-22T09:07:30.431Z"
    },
    {
      "number": "1.0.2",
      "date": "2016-04-25T15:44:29.614Z"
    },
    {
      "number": "1.0.3",
      "date": "2016-04-29T08:53:53.427Z"
    },
    {
      "number": "1.0.4",
      "date": "2016-07-14T08:44:29.973Z"
    },
    {
      "number": "1.0.5",
      "date": "2016-07-19T10:45:43.433Z"
    },
    {
      "number": "1.0.6",
      "date": "2016-07-20T02:57:37.908Z"
    },
    {
      "number": "1.0.7",
      "date": "2016-08-21T03:43:28.173Z"
    },
    {
      "number": "1.0.8",
      "date": "2016-09-07T05:59:42.498Z"
    },
    {
      "number": "1.0.9",
      "date": "2016-09-20T05:59:11.790Z"
    },
    {
      "number": "1.0.10",
      "date": "2016-09-20T08:18:09.328Z"
    }
  ],
  "created": "2016-04-18T04:34:37.463Z",
  "modified": "2016-09-20T08:18:09.328Z",
  "lastPublisher": {
    "name": "ziczhu",
    "email": "zic.zhu@gmail.com"
  },
  "owners": [
    {
      "name": "xudafeng",
      "email": "xudafeng@126.com"
    },
    {
      "name": "ziczhu",
      "email": "zic.zhu@gmail.com"
    }
  ],
  "readme": "# Macaca WD Client\n\n[![Gitter Chat][gitter-image]][gitter-url]\n[![NPM version][npm-image]][npm-url]\n[![build status][travis-image]][travis-url]\n[![node version][node-image]][node-url]\n\n[npm-image]: https://img.shields.io/npm/v/macaca-wd.svg?style=flat-square\n[npm-url]: https://npmjs.org/package/macaca-wd\n[travis-image]: https://img.shields.io/travis/macacajs/macaca-wd.svg?style=flat-square\n[travis-url]: https://travis-ci.org/macacajs/macaca-wd\n[node-image]: https://img.shields.io/badge/node.js-%3E=_4-green.svg?style=flat-square\n[node-url]: http://nodejs.org/download/\n[gitter-image]: https://img.shields.io/badge/GITTER-join%20chat-green.svg?style=flat-square\n[gitter-url]: https://gitter.im/alibaba/macaca\n\nMacaca WD Client is inspired by [admc/wd](https://github.com/admc/wd), according to [W3C WebDriver Spec](https://w3c.github.io/webdriver/webdriver-spec.html).\n\n## Installation\n\n```shell\n$ npm i macaca-wd --save-dev\n```\n\n## Documentation\n\n### Usage\n\n```js\nvar wd = require('macaca-wd');\n\nvar remoteConfig = {\n  host: 'localhost',\n  port: 3456\n};\n\nvar driver = wd.promiseChainRemote(remoteConfig);\n\nbefore(function() {\n  return driver.init({\n    platformName: 'desktop', // iOS, Android, Desktop\n    browserName: 'chrome'    // Chrome, Electron\n    app: path/to/app         // Only for mobile\n  });\n});\n\nafter(function() {\n  return driver\n    .sleep(1000)\n    .quit();\n});\n\nit('#1 should', function() {\n\n  ...\n\n});\n\n...\n\n```\n\n### Extend\n\n```js\nwd.addPromiseChainMethod(name, method);\n```\n\n[API](//macacajs.github.io/macaca-wd/)\n\n## Demo\n\n[Macaca Getting Started](//macacajs.github.io/macaca/getting-started.html)\n"
}