{
  "name": "nodeusbscale",
  "version": "1.0.0",
  "dependencies": {
    "bindings": "~1.2.1",
    "nan": "^2.0.0"
  },
  "description": "Node.js+Linux bindings for several USB scales (Pitney Bowes, Dymo, etc.)",
  "author": {
    "name": "Daniel O'Neill",
    "email": "doneill@akielectronics.com",
    "url": "http://akielectronics.com"
  },
  "keywords": [
    "weigh",
    "pitney bowes",
    "scale",
    "usb",
    "hiddev"
  ],
  "repository": {
    "type": "git",
    "url": "git://github.com/danieloneill/nodeusbscale.git"
  },
  "scripts": {
    "install": "(node-gyp rebuild 2> builderror.log) || (exit 1)"
  },
  "engines": {
    "node": ">=0.11.13"
  },
  "gypfile": true,
  "bugs": {
    "url": "https://github.com/danieloneill/nodeusbscale/issues"
  },
  "homepage": "https://github.com/danieloneill/nodeusbscale",
  "gitHead": "1ca77e262c7be9c380467b679cee78ff79c9503a",
  "_id": "nodeusbscale@1.0.0",
  "_shasum": "615f5e53063e5f63348612a5f467fad5acc0d598",
  "_from": ".",
  "_npmVersion": "2.11.3",
  "_nodeVersion": "0.12.7",
  "_npmUser": {
    "name": "danieloneill",
    "email": "doneill@akielectronics.com"
  },
  "dist": {
    "shasum": "615f5e53063e5f63348612a5f467fad5acc0d598",
    "tarball": "http://registry.npmjs.org/nodeusbscale/-/nodeusbscale-1.0.0.tgz"
  },
  "maintainers": [
    {
      "name": "danieloneill",
      "email": "doneill@akielectronics.com"
    }
  ],
  "directories": {}
}