{
  "name": "node-mumble-audio",
  "version": "0.2.5",
  "scripts": {
    "install": "bash ./node_modules/.bin/elinst"
  },
  "main": "index.js",
  "license": "MIT",
  "description": "A capture and playback audio api for node-mumble",
  "author": {
    "name": "Justin Chase",
    "email": "justin@evolvelabs.com",
    "url": "http://github.com/EvolveLabs"
  },
  "repository": {
    "user": "EvolveLabs",
    "repo": "node-mumble-audio",
    "host": "github.com",
    "branch": "master",
    "apiHost": "api.github.com",
    "tarball_url": "https://api.github.com/repos/EvolveLabs/node-mumble-audio/tarball/master",
    "clone_url": "https://github.com/EvolveLabs/node-mumble-audio",
    "https_url": "https://github.com/EvolveLabs/node-mumble-audio",
    "travis_url": "https://travis-ci.org/EvolveLabs/node-mumble-audio",
    "zip_url": "https://github.com/EvolveLabs/node-mumble-audio/archive/master.zip",
    "api_url": "https://api.github.com/repos/EvolveLabs/node-mumble-audio"
  },
  "contributors": [
    {
      "name": "Jeff Crouse",
      "email": "jefftimesten@gmail.com"
    }
  ],
  "engines": {
    "node": ">=3.2.0",
    "electron": "~0.32.0"
  },
  "binaries": [
    "https://s3.amazonaws.com/evolve-bin/{name}/{name}-{version}-{platform}-{arch}-{configuration}.tgz"
  ],
  "dependencies": {
    "bindings": "*",
    "electron-updater-tools": "~0.3.0"
  },
  "devDependencies": {
    "nan": "~2.0.0"
  },
  "gitHead": "3ec38993d8a2600fc74850340059f3c2284910f1",
  "homepage": "https://github.com/EvolveLabs/node-mumble-audio#readme",
  "bundleDependencies": [
    "electron-updater-tools"
  ],
  "_npmVersion": "2.13.3",
  "_nodeVersion": "3.2.0",
  "dist": {
    "shasum": "562a5748634a9caca1ffa87c29996a5799deb167",
    "tarball": "http://registry.npmjs.org/node-mumble-audio/-/node-mumble-audio-0.2.5.tgz"
  },
  "versions": [
    {
      "number": "0.1.0",
      "date": "2015-09-03T22:06:26.659Z"
    },
    {
      "number": "0.2.0",
      "date": "2015-09-18T00:48:03.041Z"
    },
    {
      "number": "0.2.1",
      "date": "2015-09-18T07:13:36.978Z"
    },
    {
      "number": "0.2.2",
      "date": "2015-09-18T18:57:48.511Z"
    },
    {
      "number": "0.2.3",
      "date": "2015-09-18T21:48:09.694Z"
    },
    {
      "number": "0.2.5",
      "date": "2015-09-19T18:38:10.503Z"
    }
  ],
  "created": "2015-09-03T22:06:26.659Z",
  "modified": "2015-10-15T02:45:46.577Z",
  "lastPublisher": {
    "name": "justinmchase",
    "email": "justin.m.chase@outlook.com"
  },
  "owners": [
    {
      "name": "justinmchase",
      "email": "justin.m.chase@outlook.com"
    }
  ],
  "readme": "node-mumble-audio\n===========\n\nThis addon uses openal to provide capture and playback devices compatible with node-mumble. \n\n## Building:\n```\n$ npm install electron-build-tools -g\n$ elb configure\n```\n\n## To Do:\n* mac / linux support (need to build openal-soft and drop binaries into deps)\n* expose apis for device enumeration and selection.\n* Hook up to CI and publish pre-built binaries.\n\n## Limitations:\n* Only supports PCM data.\n* Assumes a sample rate of 48k.\n\n## Other\nSee [node-openal](https://github.com/jefftimesten/node-openal) for a starting point to a more general openal api."
}