{
  "name": "party-youtube-downloader",
  "version": "2.4.1",
  "description": "Music downloader for party",
  "main": "./electron.js",
  "repository": {
    "user": "nemanjan00",
    "repo": "party-youtube-downloader",
    "host": "github.com",
    "branch": "master",
    "apiHost": "api.github.com",
    "tarball_url": "https://api.github.com/repos/nemanjan00/party-youtube-downloader/tarball/master",
    "clone_url": "https://github.com/nemanjan00/party-youtube-downloader",
    "https_url": "https://github.com/nemanjan00/party-youtube-downloader",
    "travis_url": "https://travis-ci.org/nemanjan00/party-youtube-downloader",
    "zip_url": "https://github.com/nemanjan00/party-youtube-downloader/archive/master.zip",
    "api_url": "https://api.github.com/repos/nemanjan00/party-youtube-downloader"
  },
  "scripts": {
    "start": "node ./index.js",
    "test": "echo \"Error: no test specified\" && exit 1"
  },
  "bin": {
    "party": "index.js"
  },
  "author": {
    "name": "nemanjan00",
    "email": "nemanjan00@gmail.com"
  },
  "license": "MIT",
  "devDependencies": {
    "grunt": "*",
    "grunt-contrib-concat": "*",
    "grunt-contrib-less": "*",
    "grunt-contrib-uglify": "*",
    "grunt-contrib-watch": "*"
  },
  "dependencies": {
    "ejs": "^2.4.1",
    "express": "^4.13.4",
    "forever": "^0.15.1",
    "ytdl-core": "^0.7.10"
  },
  "gitHead": "23a6e9f7f4f74bfe004cfc6a63cfc93b409f4268",
  "homepage": "https://github.com/nemanjan00/party-youtube-downloader#readme",
  "_npmVersion": "3.10.8",
  "_nodeVersion": "6.8.0",
  "dist": {
    "shasum": "913ed551db0316fca87c393041ccad5e047a8de5",
    "tarball": "http://registry.npmjs.org/party-youtube-downloader/-/party-youtube-downloader-2.4.1.tgz"
  },
  "versions": [
    {
      "number": "1.0.0",
      "date": "2016-02-20T10:47:56.650Z"
    },
    {
      "number": "1.0.1",
      "date": "2016-02-20T10:54:58.883Z"
    },
    {
      "number": "1.1.0",
      "date": "2016-02-20T11:00:12.898Z"
    },
    {
      "number": "1.2.0",
      "date": "2016-02-20T11:03:40.851Z"
    },
    {
      "number": "1.3.0",
      "date": "2016-02-20T11:48:51.509Z"
    },
    {
      "number": "2.0.0",
      "date": "2016-02-21T01:19:42.620Z"
    },
    {
      "number": "2.1.0",
      "date": "2016-02-21T01:29:33.311Z"
    },
    {
      "number": "2.2.0",
      "date": "2016-02-21T03:01:36.274Z"
    },
    {
      "number": "2.3.0",
      "date": "2016-02-21T03:11:40.586Z"
    },
    {
      "number": "2.3.1",
      "date": "2016-06-13T19:27:27.223Z"
    },
    {
      "number": "2.3.5",
      "date": "2016-06-13T19:53:43.639Z"
    },
    {
      "number": "2.3.7",
      "date": "2016-06-13T20:04:49.086Z"
    },
    {
      "number": "2.3.8",
      "date": "2016-06-13T20:33:18.576Z"
    },
    {
      "number": "2.4.0",
      "date": "2016-06-13T20:54:58.112Z"
    },
    {
      "number": "2.4.1",
      "date": "2016-10-29T13:54:35.169Z"
    }
  ],
  "created": "2016-02-20T10:47:56.650Z",
  "modified": "2016-10-29T13:54:35.169Z",
  "lastPublisher": {
    "name": "nemanjan00",
    "email": "nemanjan00@gmail.com"
  },
  "owners": [
    {
      "name": "nemanjan00",
      "email": "nemanjan00@gmail.com"
    }
  ]
}