{
  "name": "pomegranate-express-pug",
  "version": "1.0.0",
  "description": "A Pug/Jade renderer for Pomegranate Express ecosystem plugins.",
  "main": "index.js",
  "scripts": {
    "test": "echo \"Error: no test specified\" && exit 1"
  },
  "repository": {
    "user": "Pomegranate",
    "repo": "pomegranate-express-pug",
    "host": "github.com",
    "branch": "master",
    "apiHost": "api.github.com",
    "tarball_url": "https://api.github.com/repos/Pomegranate/pomegranate-express-pug/tarball/master",
    "clone_url": "https://github.com/Pomegranate/pomegranate-express-pug",
    "https_url": "https://github.com/Pomegranate/pomegranate-express-pug",
    "travis_url": "https://travis-ci.org/Pomegranate/pomegranate-express-pug",
    "zip_url": "https://github.com/Pomegranate/pomegranate-express-pug/archive/master.zip",
    "api_url": "https://api.github.com/repos/Pomegranate/pomegranate-express-pug"
  },
  "keywords": [],
  "author": {
    "name": "Jim Bulkowski",
    "email": "jim.b@paperelectron.com",
    "url": "http://paperelectron.com"
  },
  "license": "ISC",
  "homepage": "https://github.com/Pomegranate/pomegranate-express-pug#readme",
  "dependencies": {
    "pug": "^2.0.0-beta11"
  },
  "gitHead": "f74836c5263901ba5622a3fa88869e6746f2046d",
  "_npmVersion": "3.10.8",
  "_nodeVersion": "6.9.1",
  "dist": {
    "shasum": "fbb6a93debf36e15aa52b7fbdb9f77bf59a2abdc",
    "tarball": "https://registry.npmjs.org/pomegranate-express-pug/-/pomegranate-express-pug-1.0.0.tgz"
  },
  "versions": [
    {
      "number": "1.0.0",
      "date": "2017-02-10T06:50:53.155Z"
    }
  ],
  "created": "2017-02-10T06:50:53.155Z",
  "modified": "2017-02-10T06:50:53.155Z",
  "lastPublisher": {
    "name": "paperelectron",
    "email": "jim.bulkowski@paperelectron.com"
  },
  "owners": [
    {
      "name": "paperelectron",
      "email": "jim.bulkowski@paperelectron.com"
    }
  ]
}