{
  "name": "react-scripts-ts-sp",
  "version": "0.2.9",
  "description": "SharePoint TypeScript and create-react-app",
  "repository": {
    "user": "yosharepoint",
    "repo": "create-react-app",
    "host": "github.com",
    "branch": "master",
    "apiHost": "api.github.com",
    "tarball_url": "https://api.github.com/repos/yosharepoint/create-react-app/tarball/master",
    "clone_url": "https://github.com/yosharepoint/create-react-app",
    "https_url": "https://github.com/yosharepoint/create-react-app",
    "travis_url": "https://travis-ci.org/yosharepoint/create-react-app",
    "zip_url": "https://github.com/yosharepoint/create-react-app/archive/master.zip",
    "api_url": "https://api.github.com/repos/yosharepoint/create-react-app"
  },
  "license": "BSD-3-Clause",
  "engines": {
    "node": ">=4"
  },
  "files": [
    ".babelrc",
    "config",
    "bin",
    "scripts",
    "template",
    "utils"
  ],
  "bin": {
    "react-scripts-ts-sp": "./bin/react-scripts-ts-sp.js"
  },
  "devDependencies": {
    "react": "15.4.1",
    "react-dom": "15.4.1"
  },
  "dependencies": {
    "@types/electron": "1.4.30",
    "@types/react": "0.14.55",
    "@types/react-dom": "0.14.20",
    "@types/jest": "16.0.3",
    "autoprefixer": "6.6.0",
    "case-sensitive-paths-webpack-plugin": "1.1.4",
    "chalk": "1.1.3",
    "connect-history-api-fallback": "1.3.0",
    "cross-spawn": "4.0.2",
    "css-loader": "0.26.1",
    "detect-port": "1.0.7",
    "dotenv": "2.0.0",
    "extract-text-webpack-plugin": "1.0.1",
    "file-loader": "0.9.0",
    "filesize": "3.3.0",
    "fs-extra": "1.0.0",
    "gzip-size": "3.0.0",
    "html-webpack-plugin": "2.25.0",
    "http-proxy-middleware": "0.17.3",
    "jest": "17.0.2",
    "json-loader": "0.5.4",
    "mobx-react-devtools": "4.2.10",
    "object-assign": "4.1.0",
    "postcss-loader": "1.2.1",
    "promise": "7.1.1",
    "react-dev-utils": "^0.4.2",
    "recursive-readdir": "2.1.0",
    "strip-ansi": "3.0.1",
    "style-loader": "0.13.1",
    "ts-loader": "1.3.3",
    "tslint": "^4.2.0",
    "tslint-loader": "^3.3.0",
    "tslint-react": "^2.2.0",
    "typescript": "^2.1.4",
    "url-loader": "0.5.7",
    "webpack": "1.14.0",
    "webpack-dev-server": "1.16.2",
    "webpack-manifest-plugin": "1.1.0",
    "whatwg-fetch": "1.0.0",
    "electron-prebuilt": "1.4.13",
    "mobx": "2.7.0",
    "mobx-react": "4.0.4",
    "office-ui-fabric-react": "0.82.4",
    "node-sass": "4.1.1",
    "sass-loader": "4.1.1",
    "sp-pnp-js": "1.0.6",
    "fsevents": "1.0.15"
  },
  "optionalDependencies": {
    "fsevents": "1.0.15"
  },
  "homepage": "https://github.com/yosharepoint/create-react-app#readme",
  "scripts": {},
  "_npmVersion": "4.0.5",
  "_nodeVersion": "7.3.0",
  "dist": {
    "shasum": "f2275772fbd9afa560fd395bf73bc6d2aae50638",
    "tarball": "http://registry.npmjs.org/react-scripts-ts-sp/-/react-scripts-ts-sp-0.2.9.tgz"
  },
  "versions": [
    {
      "number": "0.1.0",
      "date": "2017-01-03T00:59:23.368Z"
    },
    {
      "number": "0.1.1",
      "date": "2017-01-03T01:02:08.049Z"
    },
    {
      "number": "0.1.2",
      "date": "2017-01-03T01:24:24.794Z"
    },
    {
      "number": "0.1.7",
      "date": "2017-01-03T07:31:29.980Z"
    },
    {
      "number": "0.1.8",
      "date": "2017-01-03T07:51:04.679Z"
    },
    {
      "number": "0.1.9",
      "date": "2017-01-03T16:08:50.310Z"
    },
    {
      "number": "0.2.0",
      "date": "2017-01-03T16:18:43.380Z"
    },
    {
      "number": "0.2.1",
      "date": "2017-01-03T16:23:21.266Z"
    },
    {
      "number": "0.2.2",
      "date": "2017-01-03T16:25:12.701Z"
    },
    {
      "number": "0.2.3",
      "date": "2017-01-03T16:31:27.449Z"
    },
    {
      "number": "0.2.4",
      "date": "2017-01-03T16:46:00.637Z"
    },
    {
      "number": "0.2.8",
      "date": "2017-01-03T18:47:58.346Z"
    },
    {
      "number": "0.2.9",
      "date": "2017-01-03T19:04:52.221Z"
    }
  ],
  "created": "2017-01-03T00:59:23.368Z",
  "modified": "2017-01-03T19:04:52.221Z",
  "lastPublisher": {
    "name": "mike-morrison",
    "email": "tellmike@outlook.com"
  },
  "owners": [
    {
      "name": "mike-morrison",
      "email": "tellmike@outlook.com"
    }
  ]
}