{
  "name": "settings-store",
  "version": "1.3.0",
  "description": "An simple way to store user settings in Node.js or Electron apps",
  "main": "lib/settings-store.js",
  "author": {
    "name": "Pentacent"
  },
  "license": "MIT",
  "repository": {
    "type": "git",
    "url": "git+https://bitbucket.org/pentacent/settings-store.git"
  },
  "keywords": [
    "settings",
    "configuration",
    "config",
    "preferences",
    "save",
    "persist",
    "storage"
  ],
  "homepage": "https://bitbucket.org/pentacent/settings-store",
  "devDependencies": {
    "ava": "^0.18.2",
    "jsdoc": "^3.4.3",
    "minami": "^1.2.3"
  },
  "ava": {
    "files": [
      "test/*.js"
    ]
  },
  "scripts": {
    "test": "ava",
    "build-docs": "jsdoc -c jsdoc.conf -r README.md -d docs lib/"
  },
  "gitHead": "95729e5f78c4d4919e9d264689344533be1518f9",
  "_npmVersion": "3.8.6",
  "_nodeVersion": "5.11.1",
  "dist": {
    "shasum": "1ccea9a9c0718d0b3d76e707fc2a572e25517e39",
    "tarball": "https://registry.npmjs.org/settings-store/-/settings-store-1.3.0.tgz"
  },
  "stars": 1,
  "versions": [
    {
      "number": "1.0.0",
      "date": "2017-03-13T12:53:04.276Z"
    },
    {
      "number": "1.0.1",
      "date": "2017-03-13T13:01:22.217Z"
    },
    {
      "number": "1.0.2",
      "date": "2017-03-13T14:26:05.249Z"
    },
    {
      "number": "1.0.3",
      "date": "2017-03-13T14:33:11.320Z"
    },
    {
      "number": "1.0.4",
      "date": "2017-03-14T17:55:20.040Z"
    },
    {
      "number": "1.1.0",
      "date": "2017-03-16T15:28:16.903Z"
    },
    {
      "number": "1.2.0",
      "date": "2017-05-17T18:57:14.441Z"
    },
    {
      "number": "1.3.0",
      "date": "2017-07-28T08:20:22.019Z"
    }
  ],
  "created": "2017-03-13T12:53:04.276Z",
  "modified": "2017-07-28T08:20:22.019Z",
  "lastPublisher": {
    "name": "pentacent",
    "email": "npm@pentacent.com"
  },
  "owners": [
    {
      "name": "pentacent",
      "email": "npm@pentacent.com"
    }
  ]
}